{
  "pose": {
    "score": 0.7184455727829653,
    "keypoints": [
      {
        "name": "nose",
        "position": {
          "x": 307.4025265698128,
          "y": 195.2531956535863
        },
        "score": 0.9998098611831665
      },
      {
        "name": "leftEye",
        "position": {
          "x": 320.5636944227769,
          "y": 178.14892172069906
        },
        "score": 0.9996418952941895
      },
      {
        "name": "rightEye",
        "position": {
          "x": 295.9605352964119,
          "y": 179.29678363760397
        },
        "score": 0.9956566095352173
      },
      {
        "name": "leftEar",
        "position": {
          "x": 353.017806649766,
          "y": 177.07086067437632
        },
        "score": 0.9971568584442139
      },
      {
        "name": "rightEar",
        "position": {
          "x": 133.49751060354916,
          "y": 288.8362156477391
        },
        "score": 0.0675571858882904
      },
      {
        "name": "leftShoulder",
        "position": {
          "x": 404.9873244929797,
          "y": 261.0431656867204
        },
        "score": 0.9730230569839478
      },
      {
        "name": "rightShoulder",
        "position": {
          "x": 296.85044120514823,
          "y": 252.93449417716997
        },
        "score": 0.9841246008872986
      },
      {
        "name": "leftElbow",
        "position": {
          "x": 447.74159638260534,
          "y": 363.0255875617204
        },
        "score": 0.9884204864501953
      },
      {
        "name": "rightElbow",
        "position": {
          "x": 278.34541975429016,
          "y": 323.8664769035863
        },
        "score": 0.9927664995193481
      },
      {
        "name": "leftWrist",
        "position": {
          "x": 399.04717360569424,
          "y": 443.1175488890333
        },
        "score": 0.9887211918830872
      },
      {
        "name": "rightWrist",
        "position": {
          "x": 283.9599380850234,
          "y": 365.5314449064449
        },
        "score": 0.9819189310073853
      },
      {
        "name": "leftHip",
        "position": {
          "x": 380.6933441400156,
          "y": 439.52609310031187
        },
        "score": 0.4954085946083069
      },
      {
        "name": "rightHip",
        "position": {
          "x": 302.8884921021841,
          "y": 434.05147560421
        },
        "score": 0.7829157710075378
      },
      {
        "name": "leftKnee",
        "position": {
          "x": 141.55200309574883,
          "y": 374.6707299246362
        },
        "score": 0.1573587954044342
      },
      {
        "name": "rightKnee",
        "position": {
          "x": 217.54750268135726,
          "y": 306.9193615189709
        },
        "score": 0.196062833070755
      },
      {
        "name": "leftAnkle",
        "position": {
          "x": 218.491249024961,
          "y": 321.25406055093555
        },
        "score": 0.2760230004787445
      },
      {
        "name": "rightAnkle",
        "position": {
          "x": 217.30685086778473,
          "y": 321.2591768451144
        },
        "score": 0.3370085656642914
      }
    ]
  }
}