{
  "pose": {
    "score": 0.850400736226755,
    "keypoints": [
      {
        "name": "nose",
        "position": {
          "x": 331.66713387285495,
          "y": 197.11563332412942
        },
        "score": 0.999518632888794
      },
      {
        "name": "leftEye",
        "position": {
          "x": 339.8765661563963,
          "y": 187.46286118600574
        },
        "score": 0.9996387958526611
      },
      {
        "name": "rightEye",
        "position": {
          "x": 324.83436524961,
          "y": 187.93695588617464
        },
        "score": 0.9989643096923828
      },
      {
        "name": "leftEar",
        "position": {
          "x": 356.1686451833073,
          "y": 190.8467872920998
        },
        "score": 0.9964268803596497
      },
      {
        "name": "rightEar",
        "position": {
          "x": 317.12814450078,
          "y": 192.74985077475313
        },
        "score": 0.7565667629241943
      },
      {
        "name": "leftShoulder",
        "position": {
          "x": 384.12008824102963,
          "y": 233.2573333549896
        },
        "score": 0.9776434302330017
      },
      {
        "name": "rightShoulder",
        "position": {
          "x": 303.3204953198128,
          "y": 229.3730915410603
        },
        "score": 0.9899624586105347
      },
      {
        "name": "leftElbow",
        "position": {
          "x": 455.90005240834637,
          "y": 231.91528066528068
        },
        "score": 0.9773049354553223
      },
      {
        "name": "rightElbow",
        "position": {
          "x": 248.62214801092045,
          "y": 246.63741716476093
        },
        "score": 0.964367687702179
      },
      {
        "name": "leftWrist",
        "position": {
          "x": 447.3343347796412,
          "y": 279.1614556262994
        },
        "score": 0.9884427189826965
      },
      {
        "name": "rightWrist",
        "position": {
          "x": 241.0967512919267,
          "y": 293.13868405665283
        },
        "score": 0.9933925867080688
      },
      {
        "name": "leftHip",
        "position": {
          "x": 367.62410418291734,
          "y": 368.8033150337838
        },
        "score": 0.9417150020599365
      },
      {
        "name": "rightHip",
        "position": {
          "x": 310.81098868954757,
          "y": 354.80757049116426
        },
        "score": 0.9652512669563293
      },
      {
        "name": "leftKnee",
        "position": {
          "x": 361.4926018915757,
          "y": 490.0864694321726
        },
        "score": 0.5249203443527222
      },
      {
        "name": "rightKnee",
        "position": {
          "x": 264.048118174727,
          "y": 459.9647442665021
        },
        "score": 0.8345623016357422
      },
      {
        "name": "leftAnkle",
        "position": {
          "x": 142.07136371392357,
          "y": 379.1860727163462
        },
        "score": 0.15635989606380463
      },
      {
        "name": "rightAnkle",
        "position": {
          "x": 261.4749597796412,
          "y": 480.0614564384096
        },
        "score": 0.3917745053768158
      }
    ]
  }
}