{
  "pose": {
    "score": 0.8236652647747713,
    "keypoints": [
      {
        "name": "nose",
        "position": {
          "x": 325.737342774961,
          "y": 191.68511341118764
        },
        "score": 0.9996812343597412
      },
      {
        "name": "leftEye",
        "position": {
          "x": 334.56461461583467,
          "y": 183.17111263156187
        },
        "score": 0.9998786449432373
      },
      {
        "name": "rightEye",
        "position": {
          "x": 318.59030689352574,
          "y": 183.15812394425677
        },
        "score": 0.9993724226951599
      },
      {
        "name": "leftEar",
        "position": {
          "x": 349.8554809379875,
          "y": 190.94521504677755
        },
        "score": 0.9930568337440491
      },
      {
        "name": "rightEar",
        "position": {
          "x": 308.53183502340096,
          "y": 189.74194183666842
        },
        "score": 0.8264523148536682
      },
      {
        "name": "leftShoulder",
        "position": {
          "x": 371.64684087363497,
          "y": 231.71364385719855
        },
        "score": 0.9840654730796814
      },
      {
        "name": "rightShoulder",
        "position": {
          "x": 289.7195239372075,
          "y": 228.64382166872403
        },
        "score": 0.9891021847724915
      },
      {
        "name": "leftElbow",
        "position": {
          "x": 437.4345809769891,
          "y": 214.45600291547558
        },
        "score": 0.8751537799835205
      },
      {
        "name": "rightElbow",
        "position": {
          "x": 227.6270140649376,
          "y": 203.74854327735187
        },
        "score": 0.7933547496795654
      },
      {
        "name": "leftWrist",
        "position": {
          "x": 446.07878924531985,
          "y": 161.7835563929314
        },
        "score": 0.75042325258255
      },
      {
        "name": "rightWrist",
        "position": {
          "x": 232.6491504972699,
          "y": 151.21938344594597
        },
        "score": 0.8831611275672913
      },
      {
        "name": "leftHip",
        "position": {
          "x": 354.24492370319814,
          "y": 372.60076257146574
        },
        "score": 0.9488590955734253
      },
      {
        "name": "rightHip",
        "position": {
          "x": 293.5816534223869,
          "y": 373.87928794178794
        },
        "score": 0.9043641686439514
      },
      {
        "name": "leftKnee",
        "position": {
          "x": 364.84746733619346,
          "y": 487.7828275240385
        },
        "score": 0.5810543894767761
      },
      {
        "name": "rightKnee",
        "position": {
          "x": 285.5195129680187,
          "y": 485.4204091411123
        },
        "score": 0.754857063293457
      },
      {
        "name": "leftAnkle",
        "position": {
          "x": 223.27128632020282,
          "y": 315.9711518158784
        },
        "score": 0.32445189356803894
      },
      {
        "name": "rightAnkle",
        "position": {
          "x": 223.0077058551092,
          "y": 316.5806912681913
        },
        "score": 0.39502087235450745
      }
    ]
  }
}