{
  "pose": {
    "score": 0.7989845547605964,
    "keypoints": [
      {
        "name": "nose",
        "position": {
          "x": 340.70251560062405,
          "y": 197.98729149070948
        },
        "score": 0.999581515789032
      },
      {
        "name": "leftEye",
        "position": {
          "x": 351.1479865444618,
          "y": 188.61813868405667
        },
        "score": 0.9998563528060913
      },
      {
        "name": "rightEye",
        "position": {
          "x": 333.5506959340874,
          "y": 187.1906926081731
        },
        "score": 0.9995389580726624
      },
      {
        "name": "leftEar",
        "position": {
          "x": 365.6666829173167,
          "y": 195.70320113533006
        },
        "score": 0.9907241463661194
      },
      {
        "name": "rightEar",
        "position": {
          "x": 323.8452795924337,
          "y": 190.30318103560293
        },
        "score": 0.8266320824623108
      },
      {
        "name": "leftShoulder",
        "position": {
          "x": 383.5356437695008,
          "y": 232.17392760849793
        },
        "score": 0.9828140735626221
      },
      {
        "name": "rightShoulder",
        "position": {
          "x": 301.26566156396257,
          "y": 225.70556133056135
        },
        "score": 0.9822357892990112
      },
      {
        "name": "leftElbow",
        "position": {
          "x": 443.1860008775351,
          "y": 229.4700879515333
        },
        "score": 0.9628177285194397
      },
      {
        "name": "rightElbow",
        "position": {
          "x": 242.95217433697348,
          "y": 222.3281219545868
        },
        "score": 0.5221438407897949
      },
      {
        "name": "leftWrist",
        "position": {
          "x": 485.77360203783155,
          "y": 310.64055191008316
        },
        "score": 0.5041105151176453
      },
      {
        "name": "rightWrist",
        "position": {
          "x": 235.76307466361155,
          "y": 283.02090777676716
        },
        "score": 0.8072676658630371
      },
      {
        "name": "leftHip",
        "position": {
          "x": 364.13721236349454,
          "y": 363.66421071010916
        },
        "score": 0.927440345287323
      },
      {
        "name": "rightHip",
        "position": {
          "x": 305.51180406591266,
          "y": 364.4150877891112
        },
        "score": 0.924677848815918
      },
      {
        "name": "leftKnee",
        "position": {
          "x": 368.1773169364275,
          "y": 482.11744534498445
        },
        "score": 0.8892282247543335
      },
      {
        "name": "rightKnee",
        "position": {
          "x": 301.5891916926677,
          "y": 475.7039878670738
        },
        "score": 0.9266543388366699
      },
      {
        "name": "leftAnkle",
        "position": {
          "x": 157.8301421119345,
          "y": 376.5103726773649
        },
        "score": 0.16670097410678864
      },
      {
        "name": "rightAnkle",
        "position": {
          "x": 141.21750377827613,
          "y": 378.9290398421258
        },
        "score": 0.1703130304813385
      }
    ]
  }
}