{
  "pose": {
    "score": 0.7445665326188592,
    "keypoints": [
      {
        "name": "nose",
        "position": {
          "x": 343.0548581318253,
          "y": 191.64760914760916
        },
        "score": 0.9998190402984619
      },
      {
        "name": "leftEye",
        "position": {
          "x": 354.6590715191108,
          "y": 183.54511982685813
        },
        "score": 0.9998384714126587
      },
      {
        "name": "rightEye",
        "position": {
          "x": 334.58896012090486,
          "y": 182.11164383283526
        },
        "score": 0.9994829893112183
      },
      {
        "name": "leftEar",
        "position": {
          "x": 367.2754363299532,
          "y": 188.94856601643713
        },
        "score": 0.9316731691360474
      },
      {
        "name": "rightEar",
        "position": {
          "x": 323.55456562012483,
          "y": 189.38806482263516
        },
        "score": 0.7971741557121277
      },
      {
        "name": "leftShoulder",
        "position": {
          "x": 384.4078770963339,
          "y": 228.86523843555094
        },
        "score": 0.9515710473060608
      },
      {
        "name": "rightShoulder",
        "position": {
          "x": 297.3939340386116,
          "y": 223.54950014617984
        },
        "score": 0.965805172920227
      },
      {
        "name": "leftElbow",
        "position": {
          "x": 429.60517014430576,
          "y": 183.848854112526
        },
        "score": 0.9469168782234192
      },
      {
        "name": "rightElbow",
        "position": {
          "x": 244.8072926823323,
          "y": 193.75131967905406
        },
        "score": 0.5339450836181641
      },
      {
        "name": "leftWrist",
        "position": {
          "x": 386.29412051482063,
          "y": 161.4570728706471
        },
        "score": 0.5777161121368408
      },
      {
        "name": "rightWrist",
        "position": {
          "x": 198.9972637968019,
          "y": 142.14361052007538
        },
        "score": 0.6188687682151794
      },
      {
        "name": "leftHip",
        "position": {
          "x": 363.6946055967239,
          "y": 364.0050229015073
        },
        "score": 0.9326264262199402
      },
      {
        "name": "rightHip",
        "position": {
          "x": 302.21129704563185,
          "y": 365.9621881496882
        },
        "score": 0.8702793717384338
      },
      {
        "name": "leftKnee",
        "position": {
          "x": 366.68340483619346,
          "y": 492.3476887344075
        },
        "score": 0.43177929520606995
      },
      {
        "name": "rightKnee",
        "position": {
          "x": 298.5573993272231,
          "y": 482.9372705788722
        },
        "score": 0.707097589969635
      },
      {
        "name": "leftAnkle",
        "position": {
          "x": 155.1929206074493,
          "y": 374.10483124350316
        },
        "score": 0.22792191803455353
      },
      {
        "name": "rightAnkle",
        "position": {
          "x": 153.9647218701248,
          "y": 374.42530007471413
        },
        "score": 0.1651155650615692
      }
    ]
  }
}