{
  "pose": {
    "score": 0.8336216667119194,
    "keypoints": [
      {
        "name": "nose",
        "position": {
          "x": 334.854353549142,
          "y": 193.857421875
        },
        "score": 0.999426543712616
      },
      {
        "name": "leftEye",
        "position": {
          "x": 341.90546996879874,
          "y": 184.19740165345635
        },
        "score": 0.999159574508667
      },
      {
        "name": "rightEye",
        "position": {
          "x": 327.46407590678626,
          "y": 185.81996735317048
        },
        "score": 0.9971009492874146
      },
      {
        "name": "leftEar",
        "position": {
          "x": 358.5969798166927,
          "y": 187.29699275597713
        },
        "score": 0.996025800704956
      },
      {
        "name": "rightEar",
        "position": {
          "x": 321.80979426677067,
          "y": 190.18891713227652
        },
        "score": 0.6844121813774109
      },
      {
        "name": "leftShoulder",
        "position": {
          "x": 387.8883702223089,
          "y": 231.64892882666322
        },
        "score": 0.9760829210281372
      },
      {
        "name": "rightShoulder",
        "position": {
          "x": 306.8747867102184,
          "y": 231.00826525142932
        },
        "score": 0.9896014332771301
      },
      {
        "name": "leftElbow",
        "position": {
          "x": 465.19686646840876,
          "y": 227.71553404365906
        },
        "score": 0.9875456690788269
      },
      {
        "name": "rightElbow",
        "position": {
          "x": 254.38049982936818,
          "y": 241.90728137993764
        },
        "score": 0.9362784028053284
      },
      {
        "name": "leftWrist",
        "position": {
          "x": 451.58596187597504,
          "y": 276.5959690910863
        },
        "score": 0.9877339601516724
      },
      {
        "name": "rightWrist",
        "position": {
          "x": 247.19569642160687,
          "y": 294.4601497531185
        },
        "score": 0.9936538934707642
      },
      {
        "name": "leftHip",
        "position": {
          "x": 370.5517806649766,
          "y": 363.9938766891892
        },
        "score": 0.8842440247535706
      },
      {
        "name": "rightHip",
        "position": {
          "x": 313.14608521840876,
          "y": 351.6086075558732
        },
        "score": 0.9581111669540405
      },
      {
        "name": "leftKnee",
        "position": {
          "x": 355.8626352866615,
          "y": 488.5426581178535
        },
        "score": 0.5148586630821228
      },
      {
        "name": "rightKnee",
        "position": {
          "x": 245.6008677847114,
          "y": 426.70816211343555
        },
        "score": 0.6835324168205261
      },
      {
        "name": "leftAnkle",
        "position": {
          "x": 156.63018903568644,
          "y": 376.06753914371103
        },
        "score": 0.15677404403686523
      },
      {
        "name": "rightAnkle",
        "position": {
          "x": 251.7781664391576,
          "y": 433.8346726383836
        },
        "score": 0.4270266890525818
      }
    ]
  }
}